nsb_toolbox/__init__.py
nsb_toolbox/_base_questions.py
nsb_toolbox/assign.py
nsb_toolbox/classes.py
nsb_toolbox/cli.py
nsb_toolbox/db.py
nsb_toolbox/docx_utils.py
nsb_toolbox/importers.py
nsb_toolbox/tables.py
nsb_toolbox/yamlparsers.py
nsb_toolbox-0.6.0.dist-info/LICENSE.txt
nsb_toolbox-0.6.0.dist-info/METADATA
nsb_toolbox-0.6.0.dist-info/WHEEL
nsb_toolbox-0.6.0.dist-info/entry_points.txt
nsb_toolbox-0.6.0.dist-info/RECORD
