Metadata-Version: 2.1
Name: nsb-toolbox
Version: 0.6.0
Summary: Utilities for editing Science Bowl questions
Home-page: https://github.com/rishi-kulkarni/nsbtoolbox
License: LICENSE.txt
Author: Rishi Kulkarni
Author-email: rishi@kulkarni.science
Requires-Python: >=3.10.0,<4.0.0
Classifier: License :: OSI Approved :: MIT License
Classifier: License :: Other/Proprietary License
Classifier: Operating System :: OS Independent
Classifier: Programming Language :: Python :: 3
Classifier: Programming Language :: Python :: 3.10
Classifier: Programming Language :: Python :: 3.11
Classifier: Programming Language :: Python :: 3.12
Classifier: Programming Language :: Python :: 3.13
Requires-Dist: colorama (>=0.4.6,<0.5.0)
Requires-Dist: python-docx (>=1.1.0,<2.0.0)
Requires-Dist: pyyaml (>=6.0,<7.0)
Requires-Dist: scipy (>=1.15.0,<2.0.0)
Requires-Dist: typing-extensions (>=4.2.0,<5.0.0)
Project-URL: Repository, https://github.com/rishi-kulkarni/nsbtoolbox
